SR Latch/gatedsrlatch.v
module gatedsrlatch(s,r,c,q,qbar);
input s,r,c;
output q,qbar;
wire scomp,rcomp;
nand n1(scomp,s,c);
nand n2(rcomp,r,c);
nand n3(q,scomp,qbar);
nand n4(qbar,rcomp,q);
endmodule

SR Latch/gatedsrlatchtb.v
module gatedsrlatchtb;
reg s,r,c;
wire q,qbar;
gatedsrlatch DUT(.s(s),.r(r),.c(c),.q(q),.qbar(qbar));
initial
begin
$dumpfile("gatedsrlatch.vcd");
$dumpvars(0,gatedsrlatchtb);
$monitor("%0t,S=%b,R=%b,C=%b,Q=%b,Qbar=%b",$time,s,r,c,q,qbar);
c=0;
#5 s=0;r=0;
#5 c=1;
#5 s=0;r=1;
#5 s=1;r=0;
#5 s=0;r=0;
#5 c=0;
#5 c=1;
#5 s=1;r=1;
#5 s=0;r=0;
#5 c=0;
#20 $finish;
end
endmodule

SR Latch/gatedsrlatch.vcd
$date
	Thu Jul 09 12:22:47 2026
$end
$version
	Icarus Verilog
$end
$timescale
	1s
$end
$scope module gatedsrlatchtb $end
$var wire 1 ! qbar $end
$var wire 1 " q $end
$var reg 1 # c $end
$var reg 1 $ r $end
$var reg 1 % s $end
$scope module DUT $end
$var wire 1 # c $end
$var wire 1 " q $end
$var wire 1 ! qbar $end
$var wire 1 $ r $end
$var wire 1 & rcomp $end
$var wire 1 % s $end
$var wire 1 ' scomp $end
$upscope $end
$upscope $end
$enddefinitions $end
$comment Show the parameter values. $end
$dumpall
$end
#0
$dumpvars
1'
1&
x%
x$
0#
x"
x!
$end
#5
0$
0%
#10
1#
#15
0"
1!
0&
1$
#20
0!
1"
1&
0'
0$
1%
#25
1'
0%
#30
0#
#35
1#
#40
1!
0&
0'
1$
1%
#45
0"
1&
1'
0$
0%
#50
0#
